{
  "__inputs": [
    {
      "name": "DS_LOKI",
      "label": "loki",
      "description": "",
      "type": "datasource",
      "pluginId": "loki",
      "pluginName": "Loki"
    }
  ],
  "__elements": {},
  "__requires": [
    {
      "type": "grafana",
      "id": "grafana",
      "name": "Grafana",
      "version": "10.4.1"
    },
    {
      "type": "panel",
      "id": "logs",
      "name": "Logs",
      "version": ""
    },
    {
      "type": "datasource",
      "id": "loki",
      "name": "Loki",
      "version": "1.0.0"
    }
  ],
  "annotations": {
    "list": [
      {
        "builtIn": 1,
        "datasource": {
          "type": "grafana",
          "uid": "-- Grafana --"
        },
        "enable": true,
        "hide": true,
        "iconColor": "rgba(0, 211, 255, 1)",
        "name": "Annotations & Alerts",
        "type": "dashboard"
      }
    ]
  },
  "editable": true,
  "fiscalYearStartMonth": 0,
  "graphTooltip": 0,
  "id": null,
  "links": [],
  "liveNow": false,
  "panels": [
    {
      "datasource": {
        "type": "loki",
        "uid": "${DS_LOKI}"
      },
      "gridPos": {
        "h": 9,
        "w": 24,
        "x": 0,
        "y": 0
      },
      "id": 1,
      "options": {
        "dedupStrategy": "exact",
        "enableLogDetails": true,
        "prettifyLogMessage": true,
        "showCommonLabels": false,
        "showLabels": false,
        "showTime": true,
        "sortOrder": "Descending",
        "wrapLogMessage": false
      },
      "targets": [
        {
          "datasource": {
            "type": "loki",
            "uid": "${DS_LOKI}"
          },
          "editorMode": "code",
          "expr": "{container=\"$container\"}",
          "queryType": "range",
          "refId": "A"
        }
      ],
      "title": "Logs of my container",
      "type": "logs"
    }
  ],
  "refresh": "",
  "schemaVersion": 39,
  "tags": [],
  "templating": {
    "list": [
      {
        "current": {},
        "datasource": {
          "type": "loki",
          "uid": "${DS_LOKI}"
        },
        "definition": "",
        "hide": 0,
        "includeAll": false,
        "label": "container",
        "multi": false,
        "name": "container",
        "options": [],
        "query": {
          "label": "container",
          "refId": "LokiVariableQueryEditor-VariableQuery",
          "stream": "",
          "type": 1
        },
        "refresh": 1,
        "regex": "",
        "skipUrlSync": false,
        "sort": 0,
        "type": "query"
      }
    ]
  },
  "time": {
    "from": "now-5m",
    "to": "now"
  },
  "timepicker": {},
  "timezone": "",
  "title": "Show my logs",
  "uid": "b841fcc2-8573-40bd-bfec-5093f4a3421b",
  "version": 2,
  "weekStart": ""
}
